hkdfref/__init__.py
hkdfref/_hkdfref.py
hkdfref-2024.2.dist-info/LICENSE.md
hkdfref-2024.2.dist-info/METADATA
hkdfref-2024.2.dist-info/WHEEL
hkdfref-2024.2.dist-info/top_level.txt
hkdfref-2024.2.dist-info/RECORD
