Metadata-Version: 2.1
Name: hkdfref
Version: 2024.2
Summary: HMAC-base key derivation function (IETF RFC 5869) implemented with Python
Author-email: Will Fatherley <wfatherley@proton.me>
Maintainer-email: Will Fatherley <wfatherley@proton.me>
License: Copyright 2024 Will Fatherley
Project-URL: repository, https://github.com/wfatherley/hkdfref.git
Classifier: Intended Audience :: Developers
Classifier: Topic :: Security :: Cryptography
Classifier: License :: OSI Approved :: MIT License
Classifier: Programming Language :: Python :: 3
Requires-Python: >=3.9
License-File: LICENSE.md
